bitstamp_api/__init__.py
bitstamp_api/clients/base.py
bitstamp_api/clients/private.py
bitstamp_api/clients/public.py
bitstamp_api/exceptions.py
bitstamp_api/models/account_balances.py
bitstamp_api/models/base.py
bitstamp_api/models/fees.py
bitstamp_api/models/market_info.py
bitstamp_api/models/order_book.py
bitstamp_api/models/orders.py
bitstamp_api/models/tickers.py
bitstamp_api/models/transactions.py
bitstamp_api/models/withdrawal.py
bitstamp_api_client-0.1.1.dist-info/LICENSE
bitstamp_api_client-0.1.1.dist-info/METADATA
bitstamp_api_client-0.1.1.dist-info/WHEEL
bitstamp_api_client-0.1.1.dist-info/RECORD
