Metadata-Version: 2.1
Name: bitstamp-api-client
Version: 0.1.1
Summary: Bitstamp API Client
License: MIT
Author: designst
Author-email: info@designstage.ch
Requires-Python: >=3.9,<4.0
Classifier: License :: OSI Approved :: MIT License
Classifier: Programming Language :: Python :: 3
Classifier: Programming Language :: Python :: 3.9
Classifier: Programming Language :: Python :: 3.10
Classifier: Programming Language :: Python :: 3.11
Requires-Dist: flake8 (>=6.1.0,<7.0.0)
Requires-Dist: isort (>=5.12.0,<6.0.0)
Requires-Dist: pydantic (>=2.4.1,<3.0.0)
Requires-Dist: pytest (>=7.4.2,<8.0.0)
Requires-Dist: requests (>=2.31.0,<3.0.0)
